.bumpversion.cfg
.gitignore
.gitmodules
.travis.yml
COPYING
README.md
README.rst
analyze.py
dataset.py
requirements.in
requirements.txt
setup.py
wercker.yml
docs/.gitignore
docs/Makefile
docs/source/_templates
docs/source/analyze.rst
docs/source/conf.py
docs/source/index.rst
docs/source/product.rst
docs/source/reviewer.rst
docs/source/_static/image.png
docs/source/img/springer.png
helper/__init__.py
helper/algorithms.py
helper/datasets.py
rgmining_script.egg-info/PKG-INFO
rgmining_script.egg-info/SOURCES.txt
rgmining_script.egg-info/dependency_links.txt
rgmining_script.egg-info/entry_points.txt
rgmining_script.egg-info/requires.txt
rgmining_script.egg-info/top_level.txt
tests/__init__.py
tests/algorithms_test.py
tests/analyze_test.py
tests/dataset.py
tests/dataset_test.py
tests/datasets_test.py
tests/test_suite.py