Metadata-Version: 1.1
Name: rgmining-script
Version: 0.6.1
Summary: Analyzing scripts for Review Graph Mining Project.
Home-page: https://github.com/rgmining/script
Author: Junpei Kawamoto
Author-email: kawamoto.junpei@gmail.com
License: GPLv3
Platform: UNKNOWN
Classifier: Development Status :: 4 - Beta
Classifier: Intended Audience :: Science/Research
Classifier: License :: OSI Approved :: GNU General Public License v3 (GPLv3)
Classifier: Natural Language :: English
Classifier: Programming Language :: Python
Classifier: Programming Language :: Python :: 2.7
Classifier: Programming Language :: Python :: 3.6
Classifier: Topic :: Software Development :: Libraries
Classifier: Topic :: Scientific/Engineering :: Information Analysis
